<?xml version="1.0" encoding="UTF-8" standalone="yes"?>
<p:sld xmlns:a="http://schemas.openxmlformats.org/drawingml/2006/main" xmlns:r="http://schemas.openxmlformats.org/officeDocument/2006/relationships" xmlns:p="http://schemas.openxmlformats.org/presentationml/2006/main"><p:cSld><p:bg><p:bgPr><a:solidFill><a:schemeClr val="lt1"/></a:solidFill><a:effectLst/></p:bgPr></p:bg><p:spTree><p:nvGrpSpPr><p:cNvPr id="1" name="Shape 393"/><p:cNvGrpSpPr/><p:nvPr/></p:nvGrpSpPr><p:grpSpPr><a:xfrm><a:off x="0" y="0"/><a:ext cx="0" cy="0"/><a:chOff x="0" y="0"/><a:chExt cx="0" cy="0"/></a:xfrm></p:grpSpPr><p:pic><p:nvPicPr><p:cNvPr id="394" name="Google Shape;394;p25" descr="A group of people in helmets on go karts&#xA;&#xA;Description automatically generated"/><p:cNvPicPr preferRelativeResize="0"/><p:nvPr/></p:nvPicPr><p:blipFill rotWithShape="1"><a:blip r:embed="rId3"><a:alphaModFix/></a:blip><a:srcRect l="1731" r="1731"/><a:stretch/></p:blipFill><p:spPr><a:xfrm><a:off x="4166505" y="10"/><a:ext cx="4444096" cy="3067040"/></a:xfrm><a:prstGeom prst="rect"><a:avLst/></a:prstGeom><a:noFill/><a:ln><a:noFill/></a:ln></p:spPr></p:pic><p:pic><p:nvPicPr><p:cNvPr id="395" name="Google Shape;395;p25" descr="A group of people posing for a photo&#xA;&#xA;Description automatically generated"/><p:cNvPicPr preferRelativeResize="0"/><p:nvPr/></p:nvPicPr><p:blipFill rotWithShape="1"><a:blip r:embed="rId4"><a:alphaModFix/></a:blip><a:srcRect t="25382" b="25382"/><a:stretch/></p:blipFill><p:spPr><a:xfrm><a:off x="-1" y="3790950"/><a:ext cx="8305800" cy="3067051"/></a:xfrm><a:prstGeom prst="rect"><a:avLst/></a:prstGeom><a:noFill/><a:ln><a:noFill/></a:ln></p:spPr></p:pic><p:sp><p:nvSpPr><p:cNvPr id="396" name="Google Shape;396;p25"/><p:cNvSpPr/><p:nvPr/></p:nvSpPr><p:spPr><a:xfrm><a:off x="0" y="0"/><a:ext cx="5155454" cy="4845530"/></a:xfrm><a:custGeom><a:avLst/><a:gdLst/><a:ahLst/><a:cxnLst/><a:rect l="l" t="t" r="r" b="b"/><a:pathLst><a:path w="5155454" h="4845530" extrusionOk="0"><a:moveTo><a:pt x="0" y="0"/></a:moveTo><a:lnTo><a:pt x="4766270" y="0"/></a:lnTo><a:lnTo><a:pt x="4896671" y="270697"/></a:lnTo><a:cubicBezTo><a:pt x="5063308" y="664671"/><a:pt x="5155454" y="1097822"/><a:pt x="5155454" y="1552495"/></a:cubicBezTo><a:cubicBezTo><a:pt x="5155454" y="3371188"/><a:pt x="3681112" y="4845530"/><a:pt x="1862419" y="4845530"/></a:cubicBezTo><a:cubicBezTo><a:pt x="1180409" y="4845530"/><a:pt x="546824" y="4638201"/><a:pt x="21252" y="4283132"/></a:cubicBezTo><a:lnTo><a:pt x="0" y="4267240"/></a:lnTo><a:close/></a:path></a:pathLst></a:custGeom><a:solidFill><a:schemeClr val="lt1"/></a:solidFill><a:ln><a:noFill/></a:ln></p:spPr><p:txBody><a:bodyPr spcFirstLastPara="1" wrap="square" lIns="91425" tIns="45700" rIns="91425" bIns="45700" anchor="ctr" anchorCtr="0"><a:noAutofit/></a:bodyPr><a:lstStyle/><a:p><a:pPr marL="0" marR="0" lvl="0" indent="0" algn="ctr" rtl="0"><a:lnSpc><a:spcPct val="100000"/></a:lnSpc><a:spcBef><a:spcPts val="0"/></a:spcBef><a:spcAft><a:spcPts val="0"/></a:spcAft><a:buClr><a:schemeClr val="lt1"/></a:buClr><a:buSzPts val="1800"/><a:buFont typeface="Calibri"/><a:buNone/></a:pPr><a:endParaRPr sz="1800" b="0" i="0" u="none" strike="noStrike" cap="none"><a:solidFill><a:srgbClr val="FFFFFF"/></a:solidFill><a:latin typeface="Calibri"/><a:ea typeface="Calibri"/><a:cs typeface="Calibri"/><a:sym typeface="Calibri"/></a:endParaRPr></a:p></p:txBody></p:sp><p:pic><p:nvPicPr><p:cNvPr id="397" name="Google Shape;397;p25" descr="A group of girls holding balloons&#xA;&#xA;Description automatically generated"/><p:cNvPicPr preferRelativeResize="0"/><p:nvPr/></p:nvPicPr><p:blipFill rotWithShape="1"><a:blip r:embed="rId5"><a:alphaModFix/></a:blip><a:srcRect t="14731" b="14730"/><a:stretch/></p:blipFill><p:spPr><a:xfrm><a:off x="1" y="2"/><a:ext cx="5017099" cy="4718647"/></a:xfrm><a:custGeom><a:avLst/><a:gdLst/><a:ahLst/><a:cxnLst/><a:rect l="l" t="t" r="r" b="b"/><a:pathLst><a:path w="5017099" h="4718647" extrusionOk="0"><a:moveTo><a:pt x="0" y="0"/></a:moveTo><a:lnTo><a:pt x="4599738" y="0"/></a:lnTo><a:lnTo><a:pt x="4636346" y="60259"/></a:lnTo><a:cubicBezTo><a:pt x="4879170" y="507256"/><a:pt x="5017099" y="1019504"/><a:pt x="5017099" y="1563967"/></a:cubicBezTo><a:cubicBezTo><a:pt x="5017099" y="3306249"/><a:pt x="3604701" y="4718647"/><a:pt x="1862419" y="4718647"/></a:cubicBezTo><a:cubicBezTo><a:pt x="1209063" y="4718647"/><a:pt x="602098" y="4520029"/><a:pt x="98607" y="4179877"/></a:cubicBezTo><a:lnTo><a:pt x="0" y="4106140"/></a:lnTo><a:close/></a:path></a:pathLst></a:custGeom><a:noFill/><a:ln><a:noFill/></a:ln></p:spPr></p:pic><p:sp><p:nvSpPr><p:cNvPr id="398" name="Google Shape;398;p25"/><p:cNvSpPr/><p:nvPr/></p:nvSpPr><p:spPr><a:xfrm><a:off x="6148480" y="1563968"/><a:ext cx="6043520" cy="5294033"/></a:xfrm><a:custGeom><a:avLst/><a:gdLst/><a:ahLst/><a:cxnLst/><a:rect l="l" t="t" r="r" b="b"/><a:pathLst><a:path w="6043520" h="5294033" extrusionOk="0"><a:moveTo><a:pt x="3600823" y="0"/></a:moveTo><a:cubicBezTo><a:pt x="4470871" y="0"/><a:pt x="5268847" y="308574"/><a:pt x="5891281" y="822253"/></a:cubicBezTo><a:lnTo><a:pt x="6043520" y="960617"/></a:lnTo><a:lnTo><a:pt x="6043520" y="5294033"/></a:lnTo><a:lnTo><a:pt x="423445" y="5294033"/></a:lnTo><a:lnTo><a:pt x="282971" y="5002426"/></a:lnTo><a:cubicBezTo><a:pt x="100759" y="4571630"/><a:pt x="0" y="4097993"/><a:pt x="0" y="3600823"/></a:cubicBezTo><a:cubicBezTo><a:pt x="0" y="1612143"/><a:pt x="1612143" y="0"/><a:pt x="3600823" y="0"/></a:cubicBezTo><a:close/></a:path></a:pathLst></a:custGeom><a:solidFill><a:schemeClr val="lt1"/></a:solidFill><a:ln><a:noFill/></a:ln></p:spPr><p:txBody><a:bodyPr spcFirstLastPara="1" wrap="square" lIns="91425" tIns="45700" rIns="91425" bIns="45700" anchor="ctr" anchorCtr="0"><a:noAutofit/></a:bodyPr><a:lstStyle/><a:p><a:pPr marL="0" marR="0" lvl="0" indent="0" algn="ctr" rtl="0"><a:lnSpc><a:spcPct val="100000"/></a:lnSpc><a:spcBef><a:spcPts val="0"/></a:spcBef><a:spcAft><a:spcPts val="0"/></a:spcAft><a:buClr><a:schemeClr val="lt1"/></a:buClr><a:buSzPts val="1800"/><a:buFont typeface="Calibri"/><a:buNone/></a:pPr><a:endParaRPr sz="1800" b="0" i="0" u="none" strike="noStrike" cap="none"><a:solidFill><a:srgbClr val="FFFFFF"/></a:solidFill><a:latin typeface="Calibri"/><a:ea typeface="Calibri"/><a:cs typeface="Calibri"/><a:sym typeface="Calibri"/></a:endParaRPr></a:p></p:txBody></p:sp><p:pic><p:nvPicPr><p:cNvPr id="399" name="Google Shape;399;p25" descr="A group of people in a room&#xA;&#xA;Description automatically generated"/><p:cNvPicPr preferRelativeResize="0"/><p:nvPr/></p:nvPicPr><p:blipFill rotWithShape="1"><a:blip r:embed="rId6"><a:alphaModFix/></a:blip><a:srcRect t="17257" b="17256"/><a:stretch/></p:blipFill><p:spPr><a:xfrm><a:off x="6283728" y="1699213"/><a:ext cx="5908273" cy="5158786"/></a:xfrm><a:custGeom><a:avLst/><a:gdLst/><a:ahLst/><a:cxnLst/><a:rect l="l" t="t" r="r" b="b"/><a:pathLst><a:path w="5908273" h="5158786" extrusionOk="0"><a:moveTo><a:pt x="3465576" y="0"/></a:moveTo><a:cubicBezTo><a:pt x="4302945" y="0"/><a:pt x="5070948" y="296984"/><a:pt x="5670004" y="791369"/></a:cubicBezTo><a:lnTo><a:pt x="5908273" y="1007923"/></a:lnTo><a:lnTo><a:pt x="5908273" y="5158786"/></a:lnTo><a:lnTo><a:pt x="443374" y="5158786"/></a:lnTo><a:lnTo><a:pt x="418277" y="5117476"/></a:lnTo><a:cubicBezTo><a:pt x="151523" y="4626427"/><a:pt x="0" y="4063697"/><a:pt x="0" y="3465576"/></a:cubicBezTo><a:cubicBezTo><a:pt x="0" y="1551591"/><a:pt x="1551591" y="0"/><a:pt x="3465576" y="0"/></a:cubicBezTo><a:close/></a:path></a:pathLst></a:custGeom><a:noFill/><a:ln><a:noFill/></a:ln></p:spPr></p:pic><p:sp><p:nvSpPr><p:cNvPr id="400" name="Google Shape;400;p25"/><p:cNvSpPr/><p:nvPr/></p:nvSpPr><p:spPr><a:xfrm><a:off x="3150534" y="1716727"/><a:ext cx="4572000" cy="4572000"/></a:xfrm><a:prstGeom prst="ellipse"><a:avLst/></a:prstGeom><a:solidFill><a:schemeClr val="lt1"/></a:solidFill><a:ln><a:noFill/></a:ln></p:spPr><p:txBody><a:bodyPr spcFirstLastPara="1" wrap="square" lIns="91425" tIns="45700" rIns="91425" bIns="45700" anchor="ctr" anchorCtr="0"><a:noAutofit/></a:bodyPr><a:lstStyle/><a:p><a:pPr marL="0" marR="0" lvl="0" indent="0" algn="ctr" rtl="0"><a:lnSpc><a:spcPct val="100000"/></a:lnSpc><a:spcBef><a:spcPts val="0"/></a:spcBef><a:spcAft><a:spcPts val="0"/></a:spcAft><a:buClr><a:schemeClr val="lt1"/></a:buClr><a:buSzPts val="1800"/><a:buFont typeface="Calibri"/><a:buNone/></a:pPr><a:endParaRPr sz="1800" b="0" i="0" u="none" strike="noStrike" cap="none"><a:solidFill><a:srgbClr val="FFFFFF"/></a:solidFill><a:latin typeface="Calibri"/><a:ea typeface="Calibri"/><a:cs typeface="Calibri"/><a:sym typeface="Calibri"/></a:endParaRPr></a:p></p:txBody></p:sp><p:pic><p:nvPicPr><p:cNvPr id="401" name="Google Shape;401;p25" descr="A group of people posing for a photo&#xA;&#xA;Description automatically generated"/><p:cNvPicPr preferRelativeResize="0"/><p:nvPr/></p:nvPicPr><p:blipFill rotWithShape="1"><a:blip r:embed="rId7"><a:alphaModFix/></a:blip><a:srcRect l="12500" r="12500"/><a:stretch/></p:blipFill><p:spPr><a:xfrm><a:off x="3287694" y="1853886"/><a:ext cx="4297680" cy="4297680"/></a:xfrm><a:custGeom><a:avLst/><a:gdLst/><a:ahLst/><a:cxnLst/><a:rect l="l" t="t" r="r" b="b"/><a:pathLst><a:path w="4297680" h="4297680" extrusionOk="0"><a:moveTo><a:pt x="2148840" y="0"/></a:moveTo><a:cubicBezTo><a:pt x="3335612" y="0"/><a:pt x="4297680" y="962068"/><a:pt x="4297680" y="2148840"/></a:cubicBezTo><a:cubicBezTo><a:pt x="4297680" y="3335612"/><a:pt x="3335612" y="4297680"/><a:pt x="2148840" y="4297680"/></a:cubicBezTo><a:cubicBezTo><a:pt x="962068" y="4297680"/><a:pt x="0" y="3335612"/><a:pt x="0" y="2148840"/></a:cubicBezTo><a:cubicBezTo><a:pt x="0" y="962068"/><a:pt x="962068" y="0"/><a:pt x="2148840" y="0"/></a:cubicBezTo><a:close/></a:path></a:pathLst></a:custGeom><a:noFill/><a:ln><a:noFill/></a:ln></p:spPr></p:pic><p:sp><p:nvSpPr><p:cNvPr id="402" name="Google Shape;402;p25"/><p:cNvSpPr/><p:nvPr/></p:nvSpPr><p:spPr><a:xfrm><a:off x="7762313" y="-1"/><a:ext cx="4444096" cy="3211788"/></a:xfrm><a:custGeom><a:avLst/><a:gdLst/><a:ahLst/><a:cxnLst/><a:rect l="l" t="t" r="r" b="b"/><a:pathLst><a:path w="4444096" h="3211788" extrusionOk="0"><a:moveTo><a:pt x="5102" y="0"/></a:moveTo><a:lnTo><a:pt x="4444096" y="0"/></a:lnTo><a:lnTo><a:pt x="4444096" y="2908319"/></a:lnTo><a:lnTo><a:pt x="4321598" y="2967330"/></a:lnTo><a:cubicBezTo><a:pt x="3949433" y="3124742"/><a:pt x="3540258" y="3211788"/><a:pt x="3110753" y="3211788"/></a:cubicBezTo><a:cubicBezTo><a:pt x="1392732" y="3211788"/><a:pt x="0" y="1819056"/><a:pt x="0" y="101035"/></a:cubicBezTo><a:close/></a:path></a:pathLst></a:custGeom><a:solidFill><a:schemeClr val="lt1"/></a:solidFill><a:ln><a:noFill/></a:ln></p:spPr><p:txBody><a:bodyPr spcFirstLastPara="1" wrap="square" lIns="91425" tIns="45700" rIns="91425" bIns="45700" anchor="ctr" anchorCtr="0"><a:noAutofit/></a:bodyPr><a:lstStyle/><a:p><a:pPr marL="0" marR="0" lvl="0" indent="0" algn="ctr" rtl="0"><a:spcBef><a:spcPts val="0"/></a:spcBef><a:spcAft><a:spcPts val="0"/></a:spcAft><a:buNone/></a:pPr><a:endParaRPr sz="1800"><a:solidFill><a:srgbClr val="FFFFFF"/></a:solidFill><a:latin typeface="Calibri"/><a:ea typeface="Calibri"/><a:cs typeface="Calibri"/><a:sym typeface="Calibri"/></a:endParaRPr></a:p></p:txBody></p:sp><p:pic><p:nvPicPr><p:cNvPr id="403" name="Google Shape;403;p25" descr="A group of people building a structure&#xA;&#xA;Description automatically generated"/><p:cNvPicPr preferRelativeResize="0"/><p:nvPr/></p:nvPicPr><p:blipFill rotWithShape="1"><a:blip r:embed="rId8"><a:alphaModFix/></a:blip><a:srcRect t="23302" b="23302"/><a:stretch/></p:blipFill><p:spPr><a:xfrm><a:off x="7928700" y="-1"/><a:ext cx="4277711" cy="3045402"/></a:xfrm><a:custGeom><a:avLst/><a:gdLst/><a:ahLst/><a:cxnLst/><a:rect l="l" t="t" r="r" b="b"/><a:pathLst><a:path w="4277711" h="3045402" extrusionOk="0"><a:moveTo><a:pt x="5102" y="0"/></a:moveTo><a:lnTo><a:pt x="4277711" y="0"/></a:lnTo><a:lnTo><a:pt x="4277711" y="2723810"/></a:lnTo><a:lnTo><a:pt x="4090449" y="2814019"/></a:lnTo><a:cubicBezTo><a:pt x="3738190" y="2963012"/><a:pt x="3350901" y="3045402"/><a:pt x="2944368" y="3045402"/></a:cubicBezTo><a:cubicBezTo><a:pt x="1318238" y="3045402"/><a:pt x="0" y="1727164"/><a:pt x="0" y="101034"/></a:cubicBezTo><a:close/></a:path></a:pathLst></a:custGeom><a:noFill/><a:ln><a:noFill/></a:ln></p:spPr></p:pic></p:spTree></p:cSld><p:clrMapOvr><a:masterClrMapping/></p:clrMapOvr></p:sld>